setup.py
pyflycapture2.egg-info/PKG-INFO
pyflycapture2.egg-info/SOURCES.txt
pyflycapture2.egg-info/dependency_links.txt
pyflycapture2.egg-info/requires.txt
pyflycapture2.egg-info/top_level.txt
src/_FlyCapture2Defs_C.pxd
src/_FlyCapture2_C.pxd
src/flycapture2.c
src/flycapture2.pyx
src/flycapture2_enums.pxi