Metadata-Version: 1.0
Name: pyflycapture2
Version: 0.1
Summary: python wrapper for libflycapture2 (C-API)
Home-page: http://launchpad.net/pyflycapture2
Author: Robert Jordens
Author-email: jordens@phys.ethz.ch
License: GPLv3+
Platform: UNKNOWN
